llama_index/readers/hatena_blog/__init__.py
llama_index/readers/hatena_blog/base.py
llama_index_readers_hatena_blog-0.4.1.dist-info/METADATA
llama_index_readers_hatena_blog-0.4.1.dist-info/WHEEL
llama_index_readers_hatena_blog-0.4.1.dist-info/licenses/LICENSE
llama_index_readers_hatena_blog-0.4.1.dist-info/RECORD
