Metadata-Version: 2.4
Name: llama-index-readers-hatena-blog
Version: 0.4.1
Summary: llama-index readers hatena_blog integration
Author-email: Your Name <you@example.com>
Maintainer: Shoya SHIRAKI
License-Expression: MIT
License-File: LICENSE
Keywords: blog,hatena
Requires-Python: <4.0,>=3.9
Requires-Dist: beautifulsoup4<5,>=4.12.3
Requires-Dist: llama-index-core<0.15,>=0.13.0
Requires-Dist: lxml<6,>=5.1.0
Requires-Dist: requests<3,>=2.31.0
